cz_mcp_demo1/__init__.py
cz_mcp_demo1-0.1.0.dist-info/WHEEL
cz_mcp_demo1-0.1.0.dist-info/entry_points.txt
cz_mcp_demo1-0.1.0.dist-info/METADATA
cz_mcp_demo1-0.1.0.dist-info/RECORD
