Metadata-Version: 2.3
Name: cz-mcp-demo1
Version: 0.1.0
Summary: Add your description here
Requires-Dist: mcp[cli]>=1.21.0
Requires-Python: >=3.13
